fakepilot/__init__.py
fakepilot/xray.py
fakepilot-25.5.1.dist-info/licenses/LICENSE
fakepilot-25.5.1.dist-info/METADATA
fakepilot-25.5.1.dist-info/WHEEL
fakepilot-25.5.1.dist-info/top_level.txt
fakepilot-25.5.1.dist-info/RECORD
