Metadata-Version: 2.4
Name: fakepilot
Version: 25.5.1
Summary: Scrapping tool for Trustpilot
Author: Carlos Romero Cruz
License-Expression: MIT
Project-URL: Repository, https://github.com/phoenixsite/fakepilot
Project-URL: Issues, https://github.com/phoenixsite/fakepilot/issues
Project-URL: Documentation, https://fakepilot.readthedocs.io/
Keywords: trustpilot,scrapping,beautifulsoup
Classifier: Development Status :: 5 - Production/Stable
Classifier: Programming Language :: Python :: 3
Classifier: Programming Language :: Python :: 3.9
Classifier: Programming Language :: Python :: 3.10
Classifier: Programming Language :: Python :: 3.11
Classifier: Programming Language :: Python :: 3.12
Classifier: Programming Language :: Python :: 3.13
Classifier: Intended Audience :: Science/Research
Requires-Python: >=3.9
License-File: LICENSE
Requires-Dist: beautifulsoup4>=4.12
Provides-Extra: lxml
Requires-Dist: lxml; extra == "lxml"
Dynamic: license-file
